Feedly2Instapaper-0.1.5.data/data/.env-example
feedly2instapaper/__init__.py
feedly2instapaper/__main__.py
feedly2instapaper/feedly2instapaper.py
Feedly2Instapaper-0.1.5.dist-info/LICENSE
Feedly2Instapaper-0.1.5.dist-info/METADATA
Feedly2Instapaper-0.1.5.dist-info/WHEEL
Feedly2Instapaper-0.1.5.dist-info/top_level.txt
Feedly2Instapaper-0.1.5.dist-info/RECORD
