Metadata-Version: 2.1
Name: Feedly2Instapaper
Version: 0.1.5
Summary: Feedly2Instapaper adds your "Saved for later" entries to Instapaper and removes those entries in Feedly.
Home-page: https://github.com/Barabazs/Feedly2Instapaper
Author: Barabazs
Author-email: 
License: MIT
Platform: UNKNOWN
Classifier: Programming Language :: Python :: 3
Classifier: License :: OSI Approved :: MIT License
Classifier: Operating System :: OS Independent
Requires-Python: >=3.7
Requires-Dist: instapaper (==0.4)
Requires-Dist: feedly-client (==0.25)
Requires-Dist: python-dotenv (==0.21.0)
Provides-Extra: dev
Requires-Dist: pre-commit ; extra == 'dev'
Requires-Dist: black ; extra == 'dev'
Requires-Dist: isort ; extra == 'dev'
Provides-Extra: test
